{
    "type": "indicator",
    "spec_version": "2.1",
    "id": "indicator--425184dd-2159-439a-9c42-46861531994b",
    "created": "2022-09-22T15:35:08.000Z",
    "modified": "2022-09-22T15:35:08.000Z",
    "name": "OTX pulse_name=Webscanners 2018-02-09  thru current day",
    "description": "404 NOT FOUND",
    "pattern": "[ipv4-addr:value = '185.156.172.79']",
    "pattern_type": "stix",
    "pattern_version": "2.1",
    "valid_from": "2022-09-22T15:35:08Z",
    "valid_until": "2022-12-21T00:00:00Z",
    "labels": [
        "scanning_host"
    ]
}