{
    "type": "indicator",
    "spec_version": "2.1",
    "id": "indicator--4eed036e-497f-4963-915a-0c0db2c65419",
    "created": "2022-08-12T02:20:10.000Z",
    "modified": "2022-08-12T02:20:10.000Z",
    "name": "OTX pulse_name=Webscanners 2018-02-09  thru current day",
    "description": "404 NOT FOUND",
    "pattern": "[ipv4-addr:value = '192.241.212.126']",
    "pattern_type": "stix",
    "pattern_version": "2.1",
    "valid_from": "2022-08-12T02:20:10Z",
    "valid_until": "2022-11-10T00:00:00Z",
    "labels": [
        "scanning_host"
    ]
}