{
    "type": "indicator",
    "spec_version": "2.1",
    "id": "indicator--4ab573ee-5275-43a5-b340-8c8597dcadab",
    "created": "2022-09-30T16:20:09.000Z",
    "modified": "2022-09-30T16:20:09.000Z",
    "name": "OTX pulse_name=Webscanners 2018-02-09  thru current day",
    "description": "404 NOT FOUND",
    "pattern": "[ipv4-addr:value = '192.241.220.57']",
    "pattern_type": "stix",
    "pattern_version": "2.1",
    "valid_from": "2022-09-30T16:20:09Z",
    "valid_until": "2022-12-29T00:00:00Z",
    "labels": [
        "scanning_host"
    ]
}