{
    "type": "indicator",
    "spec_version": "2.1",
    "id": "indicator--9fa7b7b8-50a5-4a20-9161-c161886226dc",
    "created": "2022-10-22T00:00:07.000Z",
    "modified": "2022-10-22T00:00:07.000Z",
    "name": "OTX pulse_name=Lion Team_Honeypots_Bruteforce_Source_IP 2022/10/21",
    "description": " / SSH bruteforce authentication activity",
    "pattern": "[ipv4-addr:value = '34.82.122.207']",
    "pattern_type": "stix",
    "pattern_version": "2.1",
    "valid_from": "2022-10-22T00:00:07Z",
    "valid_until": "2022-11-21T00:00:00Z",
    "labels": [
        "bruteforce"
    ]
}