{
    "type": "indicator",
    "spec_version": "2.1",
    "id": "indicator--4852024d-7ff0-4891-b8db-b7166552fd91",
    "created": "2022-09-10T15:45:19.000Z",
    "modified": "2022-09-10T15:45:19.000Z",
    "name": "OTX pulse_name=Webscanners 2018-02-09  thru current day",
    "description": "404 NOT FOUND",
    "pattern": "[ipv4-addr:value = '50.19.162.53']",
    "pattern_type": "stix",
    "pattern_version": "2.1",
    "valid_from": "2022-09-10T15:45:19Z",
    "valid_until": "2022-12-09T00:00:00Z",
    "labels": [
        "scanning_host"
    ]
}