{
    "type": "indicator",
    "spec_version": "2.1",
    "id": "indicator--7e9b03e8-57a6-493a-af22-2de0958a99cd",
    "created": "2017-08-24T09:26:22.000Z",
    "modified": "2017-08-24T09:26:22.000Z",
    "name": "OTX pulse_name=Operation Cleaver",
    "description": "",
    "pattern": "rule zhmimikatz   \n   {   \n      \n     meta:   \n       author = \"Cylance\"   \n       date = \"2014-12-02\"   \n       description = \"http://cylance.com/opcleaver\"   \n      \n     strings:   \n       $s1 = \"MimikatzRunner\"   \n       $s2 = \"zhmimikatz\"   \n      \n     condition:   \n       all of them   \n   }",
    "pattern_type": "yara",
    "valid_from": "2017-08-24T09:26:22Z"
}