{
    "type": "indicator",
    "spec_version": "2.1",
    "id": "indicator--139875a4-29a9-45ea-b882-ae9e6d604226",
    "created": "2022-08-02T18:50:08.000Z",
    "modified": "2022-08-02T18:50:08.000Z",
    "name": "OTX pulse_name=Webscanners 2018-02-09  thru current day",
    "description": "404 NOT FOUND",
    "pattern": "[ipv4-addr:value = '112.94.98.153']",
    "pattern_type": "stix",
    "pattern_version": "2.1",
    "valid_from": "2022-08-02T18:50:08Z",
    "valid_until": "2022-10-31T00:00:00Z",
    "labels": [
        "scanning_host"
    ]
}