{
    "type": "indicator",
    "spec_version": "2.1",
    "id": "indicator--87e89225-0ab7-48d4-a579-5ea0ca1d6136",
    "created": "2022-10-21T07:03:33.000Z",
    "modified": "2022-10-21T07:03:33.000Z",
    "name": "OTX pulse_name=New Malicious Clicker found in apps installed by 20M+ users",
    "description": "Payload delivery",
    "pattern": "[file:hashes.'SHA-256' = '262ad45c077902d603d88d3f6a44fced9905df501e529adc8f57a1358b454040']",
    "pattern_type": "stix",
    "pattern_version": "2.1",
    "valid_from": "2022-10-21T07:03:33Z"
}