{
    "type": "indicator",
    "spec_version": "2.1",
    "id": "indicator--12237660-31b0-492d-83da-f9d18a11e00d",
    "created": "2022-10-21T05:28:13.000Z",
    "modified": "2022-10-21T05:28:13.000Z",
    "name": "OTX pulse_name=Sophos X-Ops finds Attackers Using Covert Channels in Backdoor Against Devices",
    "description": "Payload delivery / Payload delivery",
    "pattern": "[file:hashes.'SHA-256' = 'b8a7d4636545f1402230166186ab681b46b8b1a08fcea6435d022ce677bd39c4']",
    "pattern_type": "stix",
    "pattern_version": "2.1",
    "valid_from": "2022-10-21T05:28:13Z"
}