{
    "type": "indicator",
    "spec_version": "2.1",
    "id": "indicator--02b9471d-c393-448e-8aab-98ef29016da7",
    "created": "2022-10-04T12:55:15.000Z",
    "modified": "2022-10-04T12:55:15.000Z",
    "name": "OTX pulse_name=Webscanners 2018-02-09  thru current day",
    "description": "404 NOT FOUND",
    "pattern": "[ipv4-addr:value = '137.184.176.235']",
    "pattern_type": "stix",
    "pattern_version": "2.1",
    "valid_from": "2022-10-04T12:55:15Z",
    "valid_until": "2023-01-02T00:00:00Z",
    "labels": [
        "scanning_host"
    ]
}