{
    "type": "indicator",
    "spec_version": "2.1",
    "id": "indicator--c919273e-597d-4e04-b123-7ad94a02b341",
    "created": "2022-08-15T12:00:11.000Z",
    "modified": "2022-08-15T12:00:11.000Z",
    "name": "OTX pulse_name=Webscanners 2018-02-09  thru current day",
    "description": "404 NOT FOUND",
    "pattern": "[ipv4-addr:value = '35.173.138.130']",
    "pattern_type": "stix",
    "pattern_version": "2.1",
    "valid_from": "2022-08-15T12:00:11Z",
    "valid_until": "2022-11-13T00:00:00Z",
    "labels": [
        "scanning_host"
    ]
}