{
    "type": "indicator",
    "spec_version": "2.1",
    "id": "indicator--de660851-4efe-4585-864d-d3a1412447f1",
    "created": "2022-10-21T06:40:08.000Z",
    "modified": "2022-10-21T06:40:08.000Z",
    "name": "OTX pulse_name=Webscanners 2018-02-09  thru current day",
    "description": "404 NOT FOUND",
    "pattern": "[ipv4-addr:value = '31.42.177.89']",
    "pattern_type": "stix",
    "pattern_version": "2.1",
    "valid_from": "2022-10-21T06:40:08Z",
    "valid_until": "2023-01-19T00:00:00Z",
    "labels": [
        "scanning_host"
    ]
}