{
    "type": "indicator",
    "spec_version": "2.1",
    "id": "indicator--f47c26f8-eba8-4de7-a027-f5bb896db37a",
    "created": "2022-08-05T18:25:08.000Z",
    "modified": "2022-08-05T18:25:08.000Z",
    "name": "OTX pulse_name=Webscanners 2018-02-09  thru current day",
    "description": "404 NOT FOUND",
    "pattern": "[ipv4-addr:value = '40.82.163.189']",
    "pattern_type": "stix",
    "pattern_version": "2.1",
    "valid_from": "2022-08-05T18:25:08Z",
    "valid_until": "2022-11-03T00:00:00Z",
    "labels": [
        "scanning_host"
    ]
}