{
    "type": "indicator",
    "spec_version": "2.1",
    "id": "indicator--fc2a0119-ce9e-4842-ba19-1708cdb81282",
    "created": "2022-08-12T14:05:14.000Z",
    "modified": "2022-08-12T14:05:14.000Z",
    "name": "OTX pulse_name=Webscanners 2018-02-09  thru current day",
    "description": "404 NOT FOUND",
    "pattern": "[ipv4-addr:value = '172.104.238.135']",
    "pattern_type": "stix",
    "pattern_version": "2.1",
    "valid_from": "2022-08-12T14:05:14Z",
    "valid_until": "2022-11-10T00:00:00Z",
    "labels": [
        "scanning_host"
    ]
}