{
    "type": "indicator",
    "spec_version": "2.1",
    "id": "indicator--41b0b433-0406-44dd-aa5a-7b5368fc304b",
    "created": "2022-08-18T04:30:16.000Z",
    "modified": "2022-08-18T04:30:16.000Z",
    "name": "OTX pulse_name=Webscanners 2018-02-09  thru current day",
    "description": "404 NOT FOUND",
    "pattern": "[ipv4-addr:value = '117.221.177.123']",
    "pattern_type": "stix",
    "pattern_version": "2.1",
    "valid_from": "2022-08-18T04:30:16Z",
    "valid_until": "2022-11-16T00:00:00Z",
    "labels": [
        "scanning_host"
    ]
}