{
    "type": "indicator",
    "spec_version": "2.1",
    "id": "indicator--8b0b5d5c-8fc2-4433-a606-a912433c6736",
    "created": "2022-10-22T06:00:02.000Z",
    "modified": "2022-10-22T06:00:02.000Z",
    "name": "OTX pulse_name=Honeypot Hits (2022-10-22)",
    "description": "SSH Attempt Host",
    "pattern": "[ipv4-addr:value = '203.124.61.245']",
    "pattern_type": "stix",
    "pattern_version": "2.1",
    "valid_from": "2022-10-22T06:00:02Z",
    "valid_until": "2022-11-21T06:00:00Z",
    "labels": [
        "scanning_host"
    ]
}