{
    "type": "indicator",
    "spec_version": "2.1",
    "id": "indicator--411dacd3-1285-4260-8b10-81e3afa5b063",
    "created": "2022-10-07T11:10:10.000Z",
    "modified": "2022-10-07T11:10:10.000Z",
    "name": "OTX pulse_name=Webscanners 2018-02-09  thru current day",
    "description": "404 NOT FOUND",
    "pattern": "[ipv4-addr:value = '85.208.72.169']",
    "pattern_type": "stix",
    "pattern_version": "2.1",
    "valid_from": "2022-10-07T11:10:10Z",
    "valid_until": "2023-01-05T00:00:00Z",
    "labels": [
        "scanning_host"
    ]
}