{
    "type": "indicator",
    "spec_version": "2.1",
    "id": "indicator--80010546-97ca-4bdb-9648-6eb64c7f9d7a",
    "created": "2022-09-29T03:25:18.000Z",
    "modified": "2022-09-29T03:25:18.000Z",
    "name": "OTX pulse_name=Webscanners 2018-02-09  thru current day",
    "description": "404 NOT FOUND",
    "pattern": "[ipv4-addr:value = '115.49.226.57']",
    "pattern_type": "stix",
    "pattern_version": "2.1",
    "valid_from": "2022-09-29T03:25:18Z",
    "valid_until": "2022-12-28T00:00:00Z",
    "labels": [
        "scanning_host"
    ]
}