{
    "type": "indicator",
    "spec_version": "2.1",
    "id": "indicator--2f92900a-586e-48dd-9c21-2d14c3622d17",
    "created": "2022-10-11T16:40:08.000Z",
    "modified": "2022-10-11T16:40:08.000Z",
    "name": "OTX pulse_name=Webscanners 2018-02-09  thru current day",
    "description": "404 NOT FOUND",
    "pattern": "[ipv4-addr:value = '106.10.122.53']",
    "pattern_type": "stix",
    "pattern_version": "2.1",
    "valid_from": "2022-10-11T16:40:08Z",
    "valid_until": "2023-01-09T00:00:00Z",
    "labels": [
        "scanning_host"
    ]
}