{
    "type": "indicator",
    "spec_version": "2.1",
    "id": "indicator--a184e546-f405-4d33-84ef-651df0205403",
    "created": "2022-10-08T05:35:07.000Z",
    "modified": "2022-10-08T05:35:07.000Z",
    "name": "OTX pulse_name=Webscanners 2018-02-09  thru current day",
    "description": "404 NOT FOUND",
    "pattern": "[ipv4-addr:value = '178.62.219.92']",
    "pattern_type": "stix",
    "pattern_version": "2.1",
    "valid_from": "2022-10-08T05:35:07Z",
    "valid_until": "2023-01-06T00:00:00Z",
    "labels": [
        "scanning_host"
    ]
}