{
    "type": "indicator",
    "spec_version": "2.1",
    "id": "indicator--65a3cbfb-bad0-49f4-bc93-fec4dfca4617",
    "created": "2022-08-11T21:55:06.000Z",
    "modified": "2022-08-11T21:55:06.000Z",
    "name": "OTX pulse_name=Webscanners 2018-02-09  thru current day",
    "description": "404 NOT FOUND",
    "pattern": "[ipv4-addr:value = '185.220.101.145']",
    "pattern_type": "stix",
    "pattern_version": "2.1",
    "valid_from": "2022-08-11T21:55:06Z",
    "valid_until": "2022-11-09T00:00:00Z",
    "labels": [
        "scanning_host"
    ]
}