{
    "type": "indicator",
    "spec_version": "2.1",
    "id": "indicator--14ff7a8c-9c0b-4315-8614-997a13180ea3",
    "created": "2022-10-21T00:00:07.000Z",
    "modified": "2022-10-21T00:00:07.000Z",
    "name": "OTX pulse_name=Lion Team_Honeypots_Bruteforce_Source_IP 2022/10/20",
    "description": " / SSH bruteforce authentication activity",
    "pattern": "[ipv4-addr:value = '178.134.60.186']",
    "pattern_type": "stix",
    "pattern_version": "2.1",
    "valid_from": "2022-10-21T00:00:07Z",
    "valid_until": "2022-11-20T00:00:00Z",
    "labels": [
        "bruteforce"
    ]
}