{
    "type": "indicator",
    "spec_version": "2.1",
    "id": "indicator--bbd1e6e5-127c-439f-b80d-8773033a4c0a",
    "created": "2022-08-16T22:55:08.000Z",
    "modified": "2022-08-16T22:55:08.000Z",
    "name": "OTX pulse_name=Webscanners 2018-02-09  thru current day",
    "description": "404 NOT FOUND",
    "pattern": "[ipv4-addr:value = '210.16.102.156']",
    "pattern_type": "stix",
    "pattern_version": "2.1",
    "valid_from": "2022-08-16T22:55:08Z",
    "valid_until": "2022-11-14T00:00:00Z",
    "labels": [
        "scanning_host"
    ]
}