{
    "type": "indicator",
    "spec_version": "2.1",
    "id": "indicator--70066632-da23-47f6-b233-8cc64571a4e3",
    "created": "2022-10-01T17:05:15.000Z",
    "modified": "2022-10-01T17:05:15.000Z",
    "name": "OTX pulse_name=Webscanners 2018-02-09  thru current day",
    "description": "404 NOT FOUND",
    "pattern": "[ipv4-addr:value = '35.86.208.0']",
    "pattern_type": "stix",
    "pattern_version": "2.1",
    "valid_from": "2022-10-01T17:05:15Z",
    "valid_until": "2022-12-30T00:00:00Z",
    "labels": [
        "scanning_host"
    ]
}