{
    "type": "indicator",
    "spec_version": "2.1",
    "id": "indicator--ce6c3d8b-5b48-49af-804e-8a4c1082083a",
    "created": "2022-08-06T01:45:17.000Z",
    "modified": "2022-08-06T01:45:17.000Z",
    "name": "OTX pulse_name=Webscanners 2018-02-09  thru current day",
    "description": "404 NOT FOUND",
    "pattern": "[ipv4-addr:value = '2.139.161.243']",
    "pattern_type": "stix",
    "pattern_version": "2.1",
    "valid_from": "2022-08-06T01:45:17Z",
    "valid_until": "2022-11-04T00:00:00Z",
    "labels": [
        "scanning_host"
    ]
}