{
    "type": "indicator",
    "spec_version": "2.1",
    "id": "indicator--b9d9964c-feb4-4a47-b7ab-3c3a197bbf78",
    "created": "2022-10-11T03:00:08.000Z",
    "modified": "2022-10-11T03:00:08.000Z",
    "name": "OTX pulse_name=Webscanners 2018-02-09  thru current day",
    "description": "404 NOT FOUND",
    "pattern": "[ipv4-addr:value = '143.110.254.145']",
    "pattern_type": "stix",
    "pattern_version": "2.1",
    "valid_from": "2022-10-11T03:00:08Z",
    "valid_until": "2023-01-09T00:00:00Z",
    "labels": [
        "scanning_host"
    ]
}