{
    "type": "indicator",
    "spec_version": "2.1",
    "id": "indicator--630bee99-9da1-4950-bcaf-e2a8a8edda90",
    "created": "2022-09-23T05:45:14.000Z",
    "modified": "2022-09-23T05:45:14.000Z",
    "name": "OTX pulse_name=Webscanners 2018-02-09  thru current day",
    "description": "404 NOT FOUND",
    "pattern": "[ipv4-addr:value = '36.37.140.93']",
    "pattern_type": "stix",
    "pattern_version": "2.1",
    "valid_from": "2022-09-23T05:45:14Z",
    "valid_until": "2022-12-22T00:00:00Z",
    "labels": [
        "scanning_host"
    ]
}